LICENSE
MANIFEST.in
README.md
requirements.txt
setup.py
redash_py/__init__.py
redash_py/client.py
redash_py/command.py
redash_py/exceptions.py
redash_py.egg-info/PKG-INFO
redash_py.egg-info/SOURCES.txt
redash_py.egg-info/dependency_links.txt
redash_py.egg-info/entry_points.txt
redash_py.egg-info/requires.txt
redash_py.egg-info/top_level.txt