Metadata-Version: 2.1
Name: redash-py
Version: 0.2.3.1
Summary: redash api client.
Home-page: https://github.com/denzow/redash-py
Author: denzow
Author-email: denzow@gmail.com
License: MIT License
